<annotation>
  <folder>C:/Users/Win11/Desktop/yolo_2/images1</folder>
  <filename>16_L_9.jpg</filename>
  <path>C:/Users/Win11/Desktop/yolo_2/images1\16_L_9.jpg</path>
  <source>
    <database>Unknown</database>
  </source>
  <size>
    <width>118</width>
    <height>118</height>
    <depth>3</depth>
  </size>
  <segmented>0</segmented>
  <object>
    <name>Spodoptera litura</name>
    <pose>Unspecified</pose>
    <truncated>0</truncated>
    <difficult>0</difficult>
    <bndbox>
      <xmin>1</xmin>
      <ymin>7</ymin>
      <xmax>117</xmax>
      <ymax>110</ymax>
    </bndbox>
  </object>
</annotation>
